LICENSE
MANIFEST.in
README.md
pyproject.toml
setup.cfg
setup.py
license_updater/__init__.py
license_updater/defaults.py
license_updater/logger.py
license_updater/version.py
license_updater.egg-info/PKG-INFO
license_updater.egg-info/SOURCES.txt
license_updater.egg-info/dependency_links.txt
license_updater.egg-info/entry_points.txt
license_updater.egg-info/not-zip-safe
license_updater.egg-info/requires.txt
license_updater.egg-info/top_level.txt
license_updater/client/__init__.py
license_updater/client/detect.py
license_updater/client/helpers.py
license_updater/client/listing.py
license_updater/client/update.py
license_updater/main/__init__.py
license_updater/main/client.py
license_updater/main/script.py
license_updater/main/updater.py
license_updater/main/updaters/__init__.py
license_updater/main/updaters/python_copyright_metadata/__init__.py
license_updater/main/updaters/python_copyright_metadata/update.py
license_updater/tests/helpers.py
license_updater/tests/test_updaters.py
license_updater/tests/data/python-copyright-updater-after.py
license_updater/tests/data/python-copyright-updater-before.py
license_updater/utils/__init__.py
license_updater/utils/fileio.py
license_updater/utils/terminal.py